hypso1_calibration/__init__.py
hypso1_calibration/main.py
hypso1_calibration/data/destriping_matrix_HYPSO-1_nominal_v1.npz
hypso1_calibration/data/destriping_matrix_HYPSO-1_wide_v1.npz
hypso1_calibration/data/radiometric_calibration_matrix_HYPSO-1_full_v1.npz
hypso1_calibration/data/radiometric_calibration_matrix_HYPSO-1_nominal_v1.npz
hypso1_calibration/data/radiometric_calibration_matrix_HYPSO-1_wide_v1.npz
hypso1_calibration/data/smile_correction_matrix_HYPSO-1_nominal_v1.npz
hypso1_calibration/data/smile_correction_matrix_HYPSO-1_wide_v1.npz
hypso1_calibration/data/spectral_bands_HYPSO-1_v1.npz
hypso1_calibration/data/spectral_calibration_matrix_HYPSO-1_full_v1.npz
hypso1_calibration/data/spectral_calibration_wavelengths_center_row_HYPSO-1.npz
hypso1_calibration-25.10.0b1.dist-info/METADATA
hypso1_calibration-25.10.0b1.dist-info/WHEEL
hypso1_calibration-25.10.0b1.dist-info/top_level.txt
hypso1_calibration-25.10.0b1.dist-info/RECORD
